promval/__init__.py
promval/error.py
promval/extractor.py
promval/subtree_extractor.py
promval/types.py
promval/validator.py
promval/parser/PromQLLexer.py
promval/parser/PromQLParser.py
promval/parser/PromQLParserListener.py
promval/parser/PromQLParserVisitor.py
promval/parser/__init__.py
promval-0.0.4.dist-info/LICENSE
promval-0.0.4.dist-info/METADATA
promval-0.0.4.dist-info/WHEEL
promval-0.0.4.dist-info/top_level.txt
promval-0.0.4.dist-info/RECORD
