Metadata-Version: 2.1
Name: promval
Version: 0.0.4
Summary: UNKNOWN
Home-page: UNKNOWN
License: UNKNOWN
Platform: UNKNOWN
License-File: LICENSE
Requires-Dist: antlr4-python3-runtime (>=4.10)
